[
  {
    "text": "Inicio",
    "icon": "home",
    "routerLink": "/dashboard"
  },
  {
    "text": "Informes",
    "icon": "information",
    "children": [
      {
        "text": "Resumen General",
        "icon": "list",
        "routerLink": "/dashboard/reports"
      },
      {
        "text": "Contratos Clasificados",
        "icon": "list",
        "routerLink": "/dashboard/reports/details"
      },
      {
        "text": "Resumen Entidades",
        "icon": "list",
        "routerLink": "/dashboard/reports/entities"
      },
      {
        "text": "Resumen General",
        "icon": "list",
        "routerLink": "/dashboard/reports-tree"
      }
    ]
  },
  {
    "text": "Contratos",
    "icon": "contracts",
    "children": [
      {
        "text": "Listar Vigentes",
        "icon": "list",
        "routerLink": "/dashboard/contracts_vigent"
      },
      {
        "text": "Listar Todos",
        "icon": "list",
        "routerLink": "/dashboard/contracts"
      },
      {
        "text": "Alertas",
        "icon": "alert",
        "routerLink": "/dashboard/alerts"
      }
    ]
  }
]
